vsanimesr/__init__.py
vsanimesr/arch_util.py
vsanimesr/interpolate.py
vsanimesr/vsr_arch.py
vsanimesr/models/AnimeSR_v1.pth
vsanimesr/models/AnimeSR_v2.pth
vsanimesr-2.0.0.dist-info/METADATA
vsanimesr-2.0.0.dist-info/WHEEL
vsanimesr-2.0.0.dist-info/licenses/LICENSE
vsanimesr-2.0.0.dist-info/RECORD
