Metadata-Version: 2.3
Name: vsanimesr
Version: 2.0.0
Summary: AnimeSR function for VapourSynth
Project-URL: Homepage, https://github.com/HolyWu/vs-animesr
Project-URL: Issues, https://github.com/HolyWu/vs-animesr/issues
Author-email: HolyWu <holywu@gmail.com>
License-File: LICENSE
Keywords: AnimeSR,PyTorch,TensorRT,VapourSynth
Classifier: Environment :: GPU :: NVIDIA CUDA
Classifier: License :: OSI Approved :: Apache Software License
Classifier: Operating System :: OS Independent
Classifier: Programming Language :: Python :: 3
Classifier: Topic :: Multimedia :: Video
Requires-Python: >=3.10
Requires-Dist: numpy
Requires-Dist: torch>=2.5.0.dev
Requires-Dist: vapoursynth>=66
